[
		{
			"id": "0",
			"active": "true",
			"owner": "false",
			"deleted": "false",
			"title": "Nice view in safe area",
			"type": "Shared",
			"bed": "1",
			"bath": "1",
			"area": "75",
			"cost": "500",
			"city": "Berlin",
			"pets": "true",
			"children": "false",
			"smoking":"true",
			"availability": "5/2/2016",
			"description": "Spacious and bright, this remodeled unit located on the 2nd floor in a gated complex. Granite tile floors, large wall-to-wall closet in bedroom, built-in storage in the bathroom.",
			"image1": "/img/listings/img1.jpeg",
			"image2": "/img/listings/img2.jpeg",
			"image3": "/img/listings/img3.jpeg",
			"phone": "(999) - 999-9999",
			"email": "email@example.com"
		},
		{
			"id": "1",
			"active": "true",
			"owner": "false",
			"deleted": "false",
			"title": "Spacious private room in Munich",
			"type": "Private",
			"bed": "2",
			"bath": "2",
			"area": "60",
			"cost": "700",
			"city": "Munich",
			"pets": "true",
			"children": "true",
			"smoking":"false",
			"availability": "2/27/2016",
			"description": "Spacious and bright, this remodeled unit located on the 2nd floor in a gated complex. Granite tile floors, large wall-to-wall closet in bedroom, built-in storage in the bathroom.",
			"image1": "/img/listings/img4.jpeg",
			"image2": "/img/listings/img5.jpeg",
			"image3": "/img/listings/img6.jpeg",
			"phone": "(999) - 999-9999",
			"email": "email@example.com"
		},
		{
			"id": "2",
			"active": "true",
			"owner": "false",
			"deleted": "false",
			"title": "Home with nice large backyard",
			"type": "Entire",
			"bed": "3",
			"bath": "2",
			"area": "43",
			"cost": "800",
			"city": "Berlin",
			"pets": "false",
			"children": "true",
			"smoking":"false",
			"availability": "5/12/2016",
			"description": "Spacious and bright, this remodeled unit located on the 2nd floor in a gated complex. Granite tile floors, large wall-to-wall closet in bedroom, built-in storage in the bathroom.",
			"image1": "/img/listings/img7.jpeg",
			"image2": "/img/listings/img8.jpeg",
			"image3": "/img/listings/img9.jpeg",
			"phone": "(999) - 999-9999",
			"email": "email@example.com"
		},
		{
			"id": "3",
			"active": "true",
			"owner": "false",
			"deleted": "false",
			"title": "Large shared room",
			"type": "Shared",
			"bed": "2",
			"bath": "2",
			"area": "36",
			"cost": "550",
			"city": "Munich",
			"pets": "true",
			"children": "false",
			"smoking":"true",
			"availability": "now",
			"description": "Spacious and bright, this remodeled unit located on the 2nd floor in a gated complex. Granite tile floors, large wall-to-wall closet in bedroom, built-in storage in the bathroom.",
			"image1": "/img/listings/img10.jpeg",
			"image2": "/img/listings/img11.jpeg",
			"image3": "/img/listings/img12.jpeg",
			"phone": "(999) - 999-9999",
			"email": "email@example.com"
		},
		{
			"id": "4",
			"active": "true",
			"owner": "false",
			"deleted": "false",
			"title": "Cozy private apartment",
			"type": "Private",
			"bed": "1",
			"bath": "1",
			"area": "44",
			"cost": "650",
			"city": "Berlin",
			"pets": "false",
			"children": "false",
			"smoking":"false",
			"availability": "3/24/2016",
			"description": "Spacious and bright, this remodeled unit located on the 2nd floor in a gated complex. Granite tile floors, large wall-to-wall closet in bedroom, built-in storage in the bathroom.",
			"image1": "/img/listings/img14.jpeg",
			"image2": "/img/listings/img15.jpeg",
			"image3": "/img/listings/img16.jpeg",
			"phone": "(999) - 999-9999",
			"email": "email@example.com"
		},
		{
			"id": "5",
			"active": "true",
			"owner": "false",
			"deleted": "false",
			"title": "Modern apartment in Berlin",
			"type": "Apartment",
			"bed": "1",
			"bath": "1",
			"area": "90",
			"cost": "450",
			"city": "Berlin",
			"pets": "true",
			"children": "true",
			"smoking":"true",
			"availability": "now",
			"description": "Spacious and bright, this remodeled unit located on the 2nd floor in a gated complex. Granite tile floors, large wall-to-wall closet in bedroom, built-in storage in the bathroom.",
			"image1": "/img/listings/img17.jpeg",
			"image2": "/img/listings/img18.jpeg",
			"image3": "/img/listings/img19.jpeg",
			"phone": "(999) - 999-9999",
			"email": "email@example.com"
		},
		{
			"id": "6",
			"active": "true",
			"owner": "false",
			"deleted": "false",
			"title": "Munich suburbs",
			"type": "Shared",
			"bed": "3",
			"bath": "2",
			"area": "76",
			"cost": "450",
			"city": "Munich",
			"pets": "true",
			"children": "true",
			"smoking":"false",
			"availability": "5/27/2016",
			"description": "Spacious and bright, this remodeled unit located on the 2nd floor in a gated complex. Granite tile floors, large wall-to-wall closet in bedroom, built-in storage in the bathroom.",
			"image1": "/img/listings/img20.jpeg",
			"image2": "/img/listings/img21.jpeg",
			"image3": "/img/listings/img22.jpeg",
			"phone": "(999) - 999-9999",
			"email": "email@example.com"			
		},

		{
			"id": "7",
			"active": "true",
			"owner": "false",
			"deleted": "false",
			"title": "Modern apartment in Berlin",
			"type": "Apartment",
			"bed": "1",
			"bath": "1",
			"area": "90",
			"cost": "450",
			"city": "Berlin",
			"pets": "true",
			"children": "true",
			"smoking":"true",
			"availability": "now",
			"description": "Spacious and bright, this remodeled unit located on the 2nd floor in a gated complex. Granite tile floors, large wall-to-wall closet in bedroom, built-in storage in the bathroom.",
			"image1": "/img/listings/img23.jpeg",
			"image2": "/img/listings/img24.jpeg",
			"image3": "/img/listings/img25.jpeg",
			"phone": "(999) - 999-9999",
			"email": "email@example.com"
		},

		{
			"id": "8",
			"active": "true",
			"owner": "false",
			"deleted": "false",
			"title": "Modern apartment in Munich",
			"type": "Apartment",
			"bed": "1",
			"bath": "1",
			"area": "90",
			"cost": "450",
			"city": "Munich",
			"pets": "true",
			"children": "true",
			"smoking":"true",
			"availability": "now",
			"description": "Spacious and bright, this remodeled unit located on the 2nd floor in a gated complex. Granite tile floors, large wall-to-wall closet in bedroom, built-in storage in the bathroom.",
			"image1": "/img/listings/img26.jpeg",
			"image2": "/img/listings/img27.jpeg",
			"image3": "/img/listings/img28.jpeg",
			"phone": "(999) - 999-9999",
			"email": "email@example.com"
		},

		{
			"id": "9",
			"active": "true",
			"owner": "false",
			"deleted": "false",
			"title": "Modern apartment in Berlin",
			"type": "Apartment",
			"bed": "1",
			"bath": "1",
			"area": "90",
			"cost": "450",
			"city": "Berlin",
			"pets": "true",
			"children": "true",
			"smoking":"true",
			"availability": "now",
			"description": "Spacious and bright, this remodeled unit located on the 2nd floor in a gated complex. Granite tile floors, large wall-to-wall closet in bedroom, built-in storage in the bathroom.",
			"image1": "/img/listings/img29.jpeg",
			"image2": "/img/listings/img1.jpeg",
			"image3": "/img/listings/img2.jpeg",
			"phone": "(999) - 999-9999",
			"email": "email@example.com"
		},

		{
			"id": "10",
			"active": "true",
			"owner": "false",
			"deleted": "false",
			"title": "Modern apartment in nice neighborhood",
			"type": "Apartment",
			"bed": "1",
			"bath": "1",
			"area": "90",
			"cost": "450",
			"city": "Munich",
			"pets": "true",
			"children": "true",
			"smoking":"true",
			"availability": "now",
			"description": "Spacious and bright, this remodeled unit located on the 2nd floor in a gated complex. Granite tile floors, large wall-to-wall closet in bedroom, built-in storage in the bathroom.",
			"image1": "/img/listings/img4.jpeg",
			"image2": "/img/listings/img2.jpeg",
			"image3": "/img/listings/img3.jpeg",
			"phone": "(999) - 999-9999",
			"email": "email@example.com"
		},

		{
			"id": "11",
			"active": "true",
			"owner": "false",
			"deleted": "false",
			"title": "Modern apartment in germany",
			"type": "Apartment",
			"bed": "1",
			"bath": "1",
			"area": "90",
			"cost": "450",
			"city": "Berlin",
			"pets": "true",
			"children": "true",
			"smoking":"true",
			"availability": "now",
			"description": "Spacious and bright, this remodeled unit located on the 2nd floor in a gated complex. Granite tile floors, large wall-to-wall closet in bedroom, built-in storage in the bathroom.",
			"image1": "/img/listings/img4.jpeg",
			"image2": "/img/listings/img5.jpeg",
			"image3": "/img/listings/img6.jpeg",
			"phone": "(999) - 999-9999",
			"email": "email@example.com"
		},

		{
			"id": "12",
			"active": "true",
			"owner": "false",
			"deleted": "false",
			"title": "Modern apartment downtown",
			"type": "Apartment",
			"bed": "1",
			"bath": "1",
			"area": "90",
			"cost": "450",
			"city": "Munich",
			"pets": "true",
			"children": "true",
			"smoking":"true",
			"availability": "now",
			"description": "Spacious and bright, this remodeled unit located on the 2nd floor in a gated complex. Granite tile floors, large wall-to-wall closet in bedroom, built-in storage in the bathroom.",
			"image1": "/img/listings/img7.jpeg",
			"image2": "/img/listings/img8.jpeg",
			"image3": "/img/listings/img9.jpeg",
			"phone": "(999) - 999-9999",
			"email": "email@example.com"
		},

		{
			"id": "13",
			"active": "true",
			"owner": "false",
			"deleted": "false",
			"title": "Bright Loft in Altstadt",
			"type": "Apartment",
			"bed": "2",
			"bath": "1",
			"area": "42",
			"cost": "350",
			"city": "Munich",
			"pets": "true",
			"children": "true",
			"smoking":"false",
			"availability": "6/21/2016",
			"description": "Spacious and bright, this remodeled unit located on the 2nd floor in a gated complex. Granite tile floors, large wall-to-wall closet in bedroom, built-in storage in the bathroom.",
			"image1": "/img/listings/img10.jpeg",
			"image2": "/img/listings/img12.jpeg",
			"image3": "/img/listings/img13.jpeg",
			"phone": "(999) - 999-9999",
			"email": "email@example.com"			
		},

		{
			"id": "14",
			"active": "true",
			"owner": "false",
			"deleted": "false",
			"title": "Munich suburbs",
			"type": "Apartment",
			"bed": "2",
			"bath": "2",
			"area": "58",
			"cost": "375",
			"city": "Munich",
			"pets": "true",
			"children": "true",
			"smoking":"false",
			"availability": "6/10/2016",
			"description": "Spacious and bright, this remodeled unit located on the 2nd floor in a gated complex. Granite tile floors, large wall-to-wall closet in bedroom, built-in storage in the bathroom.",
			"image1": "/img/listings/img14.jpeg",
			"image2": "/img/listings/img15.jpeg",
			"image3": "/img/listings/img16.jpeg",
			"phone": "(999) - 999-9999",
			"email": "email@example.com"			
		},

		{
			"id": "15",
			"active": "true",
			"owner": "false",
			"deleted": "false",
			"title": "Beautiful Condo",
			"type": "Shared",
			"bed": "3",
			"bath": "2",
			"area": "74",
			"cost": "650",
			"city": "Munich",
			"pets": "true",
			"children": "true",
			"smoking":"false",
			"availability": "4/19/2016",
			"description": "Granite tile floors, large wall-to-wall closet in bedroom, built-in storage in the bathroom.",
			"image1": "/img/listings/img17.jpeg",
			"image2": "/img/listings/img18.jpeg",
			"image3": "/img/listings/img19.jpeg",
			"phone": "(999) - 999-9999",
			"email": "email@example.com"			
		},

		{
			"id": "16",
			"active": "true",
			"owner": "false",
			"deleted": "false",
			"title": "Apartment in Kreuezberg",
			"type": "Apartment",
			"bed": "1",
			"bath": "1",
			"area": "39",
			"cost": "350",
			"city": "Berlin",
			"pets": "true",
			"children": "true",
			"smoking":"false",
			"availability": "5/22/2016",
			"description": "Spacious and bright, this remodeled unit located on the 2nd floor in a gated complex. Granite tile floors, large wall-to-wall closet in bedroom, built-in storage in the bathroom.",
			"image1": "/img/listings/img19.jpeg",
			"image2": "/img/listings/img21.jpeg",
			"image3": "/img/listings/img22.jpeg",
			"phone": "(999) - 999-9999",
			"email": "email@example.com"			
		},

		{
			"id": "17",
			"active": "true",
			"owner": "false",
			"deleted": "false",
			"title": "Large yet cozy Apartment in Friedrichshain",
			"type": "Shared",
			"bed": "2",
			"bath": "2",
			"area": "55",
			"cost": "480",
			"city": "Berlin",
			"pets": "true",
			"children": "true",
			"smoking":"false",
			"availability": "3/13/2016",
			"description": "Spacious and bright, this remodeled unit located on the 2nd floor in a gated complex. Granite tile floors, large wall-to-wall closet in bedroom, built-in storage in the bathroom.",
			"image1": "/img/listings/img23.jpeg",
			"image2": "/img/listings/img24.jpeg",
			"image3": "/img/listings/img25.jpeg",
			"phone": "(999) - 999-9999",
			"email": "email@example.com"			
		},

		{
			"id": "18",
			"active": "true",
			"owner": "false",
			"deleted": "false",
			"title": "Modern Loft in Downtown",
			"type": "Shared",
			"bed": "3",
			"bath": "2",
			"area": "73",
			"cost": "750",
			"city": "Berlin",
			"pets": "true",
			"children": "true",
			"smoking":"false",
			"availability": "3/22/2016",
			"description": "Spacious and bright, this remodeled unit located on the 2nd floor in a gated complex. Granite tile floors, large wall-to-wall closet in bedroom, built-in storage in the bathroom.",
			"image1": "/img/listings/img26.jpeg",
			"image2": "/img/listings/img27.jpeg",
			"image3": "/img/listings/img28.jpeg",
			"phone": "(999) - 999-9999",
			"email": "email@example.com"			
		}	
]